README.rst
setup.py
src/embeval/__init__.py
src/embeval/main.py
src/embeval.egg-info/PKG-INFO
src/embeval.egg-info/SOURCES.txt
src/embeval.egg-info/dependency_links.txt
src/embeval.egg-info/entry_points.txt
src/embeval.egg-info/requires.txt
src/embeval.egg-info/top_level.txt
src/embeval/core/__init__.py
src/embeval/core/commands/__init__.py
src/embeval/core/commands/semantic_similarity.py
src/embeval/core/processing/__init__.py
src/embeval/core/processing/generics.py
src/embeval/core/processing/semantic_similarity.py
src/embeval/core/stores/__init__.py
src/embeval/core/stores/semantic_similarity.py
src/embeval/core/tasks/__init__.py
src/embeval/core/tasks/semantic_similarity.py
src/embeval/core/visualization/__init__.py
src/embeval/core/visualization/text.py