Metadata-Version: 1.1
Name: embeval
Version: 0.1.3
Summary: A framework for embedding evaluation automation and visualization.
Home-page: https://github.com/RubenBranco/embeval
Author: Ruben Branco
Author-email: ruben.branco@outlook.pt
License: GPLv3
Platform: UNKNOWN
Classifier: Development Status :: 3 - Alpha
Classifier: Topic :: Scientific/Engineering :: Artificial Intelligence
Classifier: License :: OSI Approved :: GNU General Public License v3 (GPLv3)
Classifier: Programming Language :: Python :: 3.6
Classifier: Programming Language :: Python :: 3.7
